mafViper/__init__.py
mafViper/mafLoadr.py
mafViper/mafProcessing.py
mafViper/mafVisualization.py
mafViper-0.2.dist-info/LICENSE.md
mafViper-0.2.dist-info/METADATA
mafViper-0.2.dist-info/WHEEL
mafViper-0.2.dist-info/top_level.txt
mafViper-0.2.dist-info/RECORD
