Metadata-Version: 2.1
Name: mafViper
Version: 0.2
Summary: A Python package for processing, analyzing and visualizing MAF files.
Home-page: https://github.com/jrosen-code/mafViper
Author: Joseph Rosen
Author-email: joemrosen@gmail.com
License: UNKNOWN
Platform: UNKNOWN
Requires-Python: >=3.9
Requires-Dist: pandas>=2.2.2
Requires-Dist: seaborn>=0.13.2
Requires-Dist: matplotlib>=3.9.2
